{
    "controller": [
        {
            "name": "安卓端",
            "type": "Adb"
        }
    ],
    "resource": [
        {
            "name": "官服",
            "path": [
                "{PROJECT_DIR}/resource"
            ]
        },
        {
            "name": "B 服",
            "path": [
                "{PROJECT_DIR}/resource",
                "{PROJECT_DIR}/resource_bilibili"
            ]
        }
    ],
    "task": [
        {
            "name": "进入游戏",
            "entry": "0奇点时代OCRClick"
        }
    ]

}
